dora_argotranslate/__init__.py
dora_argotranslate/main.py
dora_argotranslate-0.3.12.dist-info/METADATA
dora_argotranslate-0.3.12.dist-info/WHEEL
dora_argotranslate-0.3.12.dist-info/entry_points.txt
dora_argotranslate-0.3.12.dist-info/top_level.txt
dora_argotranslate-0.3.12.dist-info/RECORD
