Metadata-Version: 2.4
Name: dora-argotranslate
Version: 0.3.12
Summary: Dora Node for Text translating using Argostranslate
Author-email: Haixuan Xavier Tao <tao.xavier@outlook.com>, Enzo Le Van <dev@enzo-le-van.fr>, Félix Huang <felix.huang.net@gmail.com>
License: MIT
Requires-Python: >=3.8
Requires-Dist: dora-rs>=0.3.9
Requires-Dist: numpy<2.0.0
Requires-Dist: argostranslate>=1.9.6
